llama_deploy/appserver/__init__.py
llama_deploy/appserver/app.py
llama_deploy/appserver/bootstrap.py
llama_deploy/appserver/configure_logging.py
llama_deploy/appserver/correlation_id.py
llama_deploy/appserver/deployment.py
llama_deploy/appserver/deployment_config_parser.py
llama_deploy/appserver/interrupts.py
llama_deploy/appserver/process_utils.py
llama_deploy/appserver/py.typed
llama_deploy/appserver/routers/__init__.py
llama_deploy/appserver/routers/deployments.py
llama_deploy/appserver/routers/status.py
llama_deploy/appserver/routers/ui_proxy.py
llama_deploy/appserver/settings.py
llama_deploy/appserver/stats.py
llama_deploy/appserver/types.py
llama_deploy/appserver/workflow_loader.py
llama_deploy/appserver/workflow_store/agent_data_store.py
llama_deploy/appserver/workflow_store/keyed_lock.py
llama_deploy/appserver/workflow_store/lru_cache.py
llama_deploy_appserver-0.4.1.dist-info/WHEEL
llama_deploy_appserver-0.4.1.dist-info/METADATA
llama_deploy_appserver-0.4.1.dist-info/RECORD
